AUTHOR.txt
CHANGES.txt
CONTRIBUTORS.txt
README.txt
setup.py
src/chameleon/__init__.py
src/chameleon.core.egg-info/PKG-INFO
src/chameleon.core.egg-info/SOURCES.txt
src/chameleon.core.egg-info/dependency_links.txt
src/chameleon.core.egg-info/namespace_packages.txt
src/chameleon.core.egg-info/not-zip-safe
src/chameleon.core.egg-info/requires.txt
src/chameleon.core.egg-info/top_level.txt